{
    "_comment": "Maps common recipe terms to keywords matching the climate database (Danish + Agribalyse)",
    "aliases": {
        "ground beef": "Beef, mince",
        "minced beef": "Beef, mince",
        "lean ground beef": "Beef, mince",
        "beef mince": "Beef, mince",
        "ground pork": "pork mince",
        "ground turkey": "turkey mince",
        "unsalted butter": "Butter, salt",
        "salted butter": "Butter, salt",
        "butter": "Butter, salt",
        "heavy cream": "Cream, whipping, 38 % fat",
        "whipping cream": "Cream, whipping, 38 % fat",
        "double cream": "Cream, whipping, 38 % fat",
        "sour cream": "Cream, cultured, 18 % fat",
        "bell pepper": "Pepper, sweet",
        "green bell pepper": "Pepper, sweet",
        "red bell pepper": "Pepper, sweet",
        "yellow bell pepper": "Pepper, sweet",
        "large eggs": "Eggs, chicken",
        "large egg": "Eggs, chicken",
        "eggs": "Eggs, chicken",
        "egg": "Eggs, chicken",
        "parmesan": "Cheese, hard, Parmesan",
        "parmesan cheese": "Cheese, hard, Parmesan",
        "parmigiano": "Cheese, hard, Parmesan",
        "mozzarella": "Cheese, semihard, Mozzarella",
        "mozzarella cheese": "Cheese, semihard, Mozzarella",
        "white sugar": "Sugar, sucrose, white",
        "granulated sugar": "Sugar, sucrose, white",
        "sugar": "Sugar, sucrose, white",
        "brown sugar": "Sugar, brown",
        "all-purpose flour": "Wheat, flour",
        "plain flour": "Wheat, flour",
        "flour": "Wheat, flour",
        "ap flour": "Wheat, flour",
        "whole milk": "Milk, whole, 3.5 % fat",
        "skim milk": "Milk, skimmed, 0.5 % fat",
        "skimmed milk": "Milk, skimmed, 0.5 % fat",
        "semi-skimmed milk": "Milk, partly skimmed, 1.5 % fat",
        "milk": "Milk, whole, 3.5 % fat",
        "vegetable oil": "oil",
        "canola oil": "oil rapeseed",
        "cooking oil": "oil",
        "olive oil": "oil olive",
        "extra virgin olive oil": "oil olive",
        "chicken breast": "Chicken, breast",
        "chicken thigh": "Chicken, leg",
        "chicken thighs": "Chicken, leg",
        "boneless chicken": "Chicken",
        "garlic cloves": "Garlic, raw",
        "garlic clove": "Garlic, raw",
        "fresh garlic": "Garlic, raw",
        "garlic": "Garlic, raw",
        "yellow onion": "Onion, raw",
        "white onion": "Onion, raw",
        "onion": "Onion, raw",
        "shallot": "Onion, raw",
        "shallots": "Onion, raw",
        "red onion": "Red onion",
        "spring onion": "Onions, spring",
        "green onion": "Onions, spring",
        "scallion": "Onions, spring",
        "yogurt": "Yogurt plain, whole milk",
        "greek yogurt": "Yogurt plain, whole milk",
        "plain yogurt": "Yogurt plain, whole milk",
        "black pepper": "Pepper, black",
        "chili pepper": "Pepper, hot chili",
        "hot pepper": "Pepper, hot chili",

        "dried oregano": "Oregano, dried",
        "dried thyme": "Thyme, dried",
        "dried rosemary": "Rosemary, dried",
        "dried sage": "Sage, dried",
        "dried parsley": "Parsley, dried",
        "dried basil": "Basil, dried",
        "dried marjoram": "Marjoram, dried",
        "oregano": "Oregano, dried",
        "thyme": "Thyme, dried",
        "rosemary": "Rosemary, dried",
        "bay leaf": "Bay, leaves",
        "bay leaves": "Bay, leaves",

        "cumin": "Cumin, seed",
        "ground cumin": "Cumin, seed",
        "paprika": "Paprika",
        "smoked paprika": "Paprika",
        "cinnamon": "Cinnamon, powder",
        "ground cinnamon": "Cinnamon, powder",
        "nutmeg": "Nutmeg",
        "ground nutmeg": "Nutmeg",
        "turmeric": "Turmeric, powder",
        "ground turmeric": "Turmeric, powder",
        "cayenne": "Cayenne pepper",
        "cayenne pepper": "Cayenne pepper",
        "chili powder": "Cayenne pepper",
        "curry powder": "Curry, powder",
        "curry": "Curry, powder",
        "coriander seeds": "Coriander, seed",
        "ground coriander": "Coriander, seed",
        "cardamom": "Cardamom, powder",
        "ground cardamom": "Cardamom, powder",
        "cloves": "Cloves",
        "ground cloves": "Cloves",
        "mustard powder": "Mustard",
        "dry mustard": "Mustard",

        "fresh basil": "Basil, fresh",
        "basil": "Basil, fresh",
        "fresh parsley": "Parsley, fresh",
        "parsley": "Parsley, fresh",
        "fresh dill": "Dill, fresh",
        "dill": "Dill, fresh",
        "fresh mint": "Mint, fresh",
        "mint": "Mint, fresh",
        "fresh cilantro": "Coriander, fresh",
        "cilantro": "Coriander, fresh",
        "coriander": "Coriander, fresh",
        "fresh thyme": "Thyme, fresh",
        "fresh rosemary": "Rosemary, fresh",
        "fresh sage": "Sage, fresh",
        "sage": "Sage, fresh",
        "fresh tarragon": "Tarragon, fresh",
        "tarragon": "Tarragon, fresh",
        "fresh chives": "Chives, raw",
        "chives": "Chives, raw",

        "salt": "Salt, table",
        "sea salt": "Salt, table",
        "kosher salt": "Salt, table",
        "table salt": "Salt, table",

        "beef stock": "Bouillon, beef, prepared",
        "beef broth": "Bouillon, beef, prepared",
        "beef bouillon": "Bouillon, beef, prepared",
        "chicken stock": "Bouillon, chicken, prepared",
        "chicken broth": "Bouillon, chicken, prepared",
        "chicken bouillon": "Bouillon, chicken, prepared",

        "tomato puree": "Tomato paste, concentrated",
        "tomato purée": "Tomato paste, concentrated",
        "tomato pureé": "Tomato paste, concentrated",
        "tomato paste": "Tomato paste, concentrated",
        "passata": "Tomato, peeled, canned",
        "tomato passata": "Tomato, peeled, canned",
        "canned tomatoes": "Tomato, peeled, canned",
        "diced tomatoes": "Tomato, peeled, canned",
        "crushed tomatoes": "Tomato, peeled, canned",
        "whole tomatoes": "Tomato, peeled, canned",
        "sun dried tomatoes": "Sundried tomatoes",
        "sundried tomatoes": "Sundried tomatoes",

        "spaghetti": "Pasta, raw",
        "linguine": "Pasta, raw",
        "fettuccine": "Pasta, raw",
        "penne": "Pasta, raw",
        "rigatoni": "Pasta, raw",
        "macaroni": "Pasta, raw",
        "fusilli": "Pasta, raw",
        "farfalle": "Pasta, raw",
        "pasta": "Pasta, raw",
        "noodles": "Pasta, raw",
        "rice noodles": "Rice noodles",

        "butternut squash": "Squash, butternut, pulp, raw",
        "butternut": "Squash, butternut, pulp, raw",
        "hokkaido": "Red kuri squash, pulp, raw",
        "hokkaido pumpkin": "Red kuri squash, pulp, raw",
        "red kuri squash": "Red kuri squash, pulp, raw",
        "kabocha": "Pumpkin, raw",
        "kabocha squash": "Pumpkin, raw",
        "acorn squash": "Squash, raw",
        "delicata squash": "Squash, raw",
        "spaghetti squash": "Squash, spaghetti, pulp, raw",
        "pumpkin": "Pumpkin, raw",
        "squash": "Squash, raw"
    }
}
